[{"model": "web.order", "pk": 1, "fields": {"user": "USK07595", "amount": 1.0, "status": "Pending", "types": "1", "provider_order_id": "order_KurQqfsOd4dgqm", "payment_id": null, "signature_id": null, "created_at": "2022-12-22T06:42:27.584Z"}}, {"model": "web.order", "pk": 2, "fields": {"user": "USK05656", "amount": 1.0, "status": "Pending", "types": "1", "provider_order_id": "order_KusBzZw4btQ2Zu", "payment_id": null, "signature_id": null, "created_at": "2022-12-22T07:27:05.351Z"}}, {"model": "web.order", "pk": 3, "fields": {"user": "USK05656", "amount": 1.0, "status": "Pending", "types": "1", "provider_order_id": "order_KusCJs2IXBgyPz", "payment_id": null, "signature_id": null, "created_at": "2022-12-22T07:27:23.962Z"}}, {"model": "web.order", "pk": 4, "fields": {"user": "USK05656", "amount": 1.0, "status": "Pending", "types": "1", "provider_order_id": "order_KusCTXT7pO7cPw", "payment_id": null, "signature_id": null, "created_at": "2022-12-22T07:27:32.786Z"}}, {"model": "web.order", "pk": 5, "fields": {"user": "USK05656", "amount": 1.0, "status": "Pending", "types": "1", "provider_order_id": "order_KusCqXpq12cWiw", "payment_id": null, "signature_id": null, "created_at": "2022-12-22T07:27:53.858Z"}}, {"model": "web.order", "pk": 6, "fields": {"user": "USK05656", "amount": 1.0, "status": "Pending", "types": "1", "provider_order_id": "order_KusDFFtcGCzyZp", "payment_id": null, "signature_id": null, "created_at": "2022-12-22T07:28:16.498Z"}}, {"model": "web.order", "pk": 7, "fields": {"user": "USK05494", "amount": 1.0, "status": "Pending", "types": "1", "provider_order_id": "order_KusHtnMEME4Dwm", "payment_id": null, "signature_id": null, "created_at": "2022-12-22T07:32:40.866Z"}}, {"model": "web.order", "pk": 8, "fields": {"user": "USK05494", "amount": 1.0, "status": "Pending", "types": "1", "provider_order_id": "order_KusIDbnC3AfKFd", "payment_id": null, "signature_id": null, "created_at": "2022-12-22T07:32:58.988Z"}}, {"model": "web.order", "pk": 9, "fields": {"user": "USK05494", "amount": 1.0, "status": "Pending", "types": "1", "provider_order_id": "order_KusIOKEHSW86Cl", "payment_id": null, "signature_id": null, "created_at": "2022-12-22T07:33:08.826Z"}}, {"model": "web.order", "pk": 10, "fields": {"user": "USK05494", "amount": 1.0, "status": "Pending", "types": "1", "provider_order_id": "order_KusgQWxbQKWY4h", "payment_id": null, "signature_id": null, "created_at": "2022-12-22T07:55:54.029Z"}}, {"model": "web.order", "pk": 11, "fields": {"user": "USK05494", "amount": 1.0, "status": "Pending", "types": "1", "provider_order_id": "order_KusgYoI853L1y6", "payment_id": null, "signature_id": null, "created_at": "2022-12-22T07:56:01.654Z"}}, {"model": "web.order", "pk": 12, "fields": {"user": "USK05494", "amount": 1.0, "status": "Pending", "types": "1", "provider_order_id": "order_KusyzyzsT1Fvsl", "payment_id": null, "signature_id": null, "created_at": "2022-12-22T08:13:28.950Z"}}, {"model": "web.order", "pk": 13, "fields": {"user": "USK05494", "amount": 1.0, "status": "Pending", "types": "1", "provider_order_id": "order_KutD3FcvmurYYu", "payment_id": null, "signature_id": null, "created_at": "2022-12-22T08:26:47.112Z"}}, {"model": "web.order", "pk": 14, "fields": {"user": "USK05494", "amount": 1.0, "status": "Pending", "types": "1", "provider_order_id": "order_KutDGaTQEJ3tVe", "payment_id": null, "signature_id": null, "created_at": "2022-12-22T08:26:59.336Z"}}, {"model": "web.order", "pk": 15, "fields": {"user": "USK05494", "amount": 1.0, "status": "Pending", "types": "1", "provider_order_id": "order_Kutqe3xIz0FB8j", "payment_id": null, "signature_id": null, "created_at": "2022-12-22T09:04:16.047Z"}}, {"model": "web.order", "pk": 16, "fields": {"user": "USK05656", "amount": 1.0, "status": "Pending", "types": "1", "provider_order_id": "order_Kuu7rDOohvCUVG", "payment_id": null, "signature_id": null, "created_at": "2022-12-22T09:20:33.727Z"}}, {"model": "web.order", "pk": 17, "fields": {"user": "USK05494", "amount": 1.0, "status": "Pending", "types": "1", "provider_order_id": "order_KvE6wBnSw7j41B", "payment_id": null, "signature_id": null, "created_at": "2022-12-23T04:53:33.745Z"}}, {"model": "web.order", "pk": 18, "fields": {"user": "USK05656", "amount": 1.0, "status": "Pending", "types": "1", "provider_order_id": "order_KvEW0S7vh3OLHs", "payment_id": null, "signature_id": null, "created_at": "2022-12-23T05:17:17.671Z"}}, {"model": "web.order", "pk": 19, "fields": {"user": "USK05656", "amount": 1.0, "status": "Pending", "types": "1", "provider_order_id": "order_KvKFqEiqzbvjFF", "payment_id": null, "signature_id": null, "created_at": "2022-12-23T10:54:09.194Z"}}, {"model": "web.order", "pk": 20, "fields": {"user": "USK05656", "amount": 1.0, "status": "Pending", "types": "1", "provider_order_id": "order_KvKj4I7h7aNQ6J", "payment_id": null, "signature_id": null, "created_at": "2022-12-23T11:21:49.263Z"}}, {"model": "web.order", "pk": 21, "fields": {"user": "USK05656", "amount": 1.0, "status": "Pending", "types": "1", "provider_order_id": "order_KvKjAExu0jfIes", "payment_id": null, "signature_id": null, "created_at": "2022-12-23T11:21:54.707Z"}}, {"model": "web.order", "pk": 22, "fields": {"user": "USK05656", "amount": 1.0, "status": "Pending", "types": "1", "provider_order_id": "order_KvKjGCbYBYQM6C", "payment_id": null, "signature_id": null, "created_at": "2022-12-23T11:22:00.176Z"}}, {"model": "web.order", "pk": 23, "fields": {"user": "USK05656", "amount": 1.0, "status": "Pending", "types": "1", "provider_order_id": "order_KvNGGBLDAQYjI1", "payment_id": null, "signature_id": null, "created_at": "2022-12-23T13:50:37.800Z"}}, {"model": "web.order", "pk": 24, "fields": {"user": "USK05494", "amount": 1.0, "status": "Pending", "types": "1", "provider_order_id": "order_KvObxwsL09PlW4", "payment_id": null, "signature_id": null, "created_at": "2022-12-23T15:09:52.335Z"}}, {"model": "web.order", "pk": 25, "fields": {"user": "USK05494", "amount": 1.0, "status": "Pending", "types": "1", "provider_order_id": "order_KvOc5tyJGeMvDK", "payment_id": null, "signature_id": null, "created_at": "2022-12-23T15:09:59.630Z"}}, {"model": "web.order", "pk": 26, "fields": {"user": "USK05494", "amount": 1.0, "status": "Pending", "types": "1", "provider_order_id": "order_KvcJgPCjxqxp8T", "payment_id": null, "signature_id": null, "created_at": "2022-12-24T04:34:16.436Z"}}, {"model": "web.order", "pk": 27, "fields": {"user": "USK05494", "amount": 1.0, "status": "Pending", "types": "", "provider_order_id": "order_KveZ1YM7puYyO0", "payment_id": null, "signature_id": null, "created_at": "2022-12-24T06:46:11.049Z"}}, {"model": "web.order", "pk": 28, "fields": {"user": "USK07595", "amount": 1.0, "status": "Pending", "types": "", "provider_order_id": "order_KveZWxYNpOPC3X", "payment_id": null, "signature_id": null, "created_at": "2022-12-24T06:46:39.807Z"}}, {"model": "web.order", "pk": 29, "fields": {"user": "USK07595", "amount": 1.0, "status": "Pending", "types": "", "provider_order_id": "order_KvefRpyKyg1MwQ", "payment_id": null, "signature_id": null, "created_at": "2022-12-24T06:52:15.936Z"}}, {"model": "web.order", "pk": 30, "fields": {"user": "USK07595", "amount": 1.0, "status": "Pending", "types": "", "provider_order_id": "order_KvevJc8CdEZbqh", "payment_id": null, "signature_id": null, "created_at": "2022-12-24T07:07:17.189Z"}}, {"model": "web.order", "pk": 31, "fields": {"user": "USK07595", "amount": 1.0, "status": "Pending", "types": "", "provider_order_id": "order_KveyOhwZ1cJ6fP", "payment_id": null, "signature_id": null, "created_at": "2022-12-24T07:10:12.279Z"}}, {"model": "web.order", "pk": 32, "fields": {"user": "USK07595", "amount": 1.0, "status": "Pending", "types": "", "provider_order_id": "order_Kvf0iIiEXa7L9w", "payment_id": null, "signature_id": null, "created_at": "2022-12-24T07:12:23.822Z"}}, {"model": "web.order", "pk": 33, "fields": {"user": "USK07595", "amount": 1.0, "status": "Pending", "types": "", "provider_order_id": "order_KvhXBLfeAbdFo1", "payment_id": null, "signature_id": null, "created_at": "2022-12-24T09:40:31.289Z"}}, {"model": "web.order", "pk": 34, "fields": {"user": "USK07595", "amount": 1.0, "status": "Pending", "types": "", "provider_order_id": "order_KvhXs5THD0hT8J", "payment_id": null, "signature_id": null, "created_at": "2022-12-24T09:41:10.429Z"}}, {"model": "web.order", "pk": 35, "fields": {"user": "USK07595", "amount": 1.0, "status": "Pending", "types": "", "provider_order_id": "order_KviyYG9dIbGnhA", "payment_id": null, "signature_id": null, "created_at": "2022-12-24T11:05:07.504Z"}}, {"model": "web.order", "pk": 36, "fields": {"user": "USK05494", "amount": 1.0, "status": "Pending", "types": "", "provider_order_id": "order_Kw122IDlGRAPL6", "payment_id": null, "signature_id": null, "created_at": "2022-12-25T04:44:54.463Z"}}, {"model": "web.order", "pk": 37, "fields": {"user": "USK07595", "amount": 1.0, "status": "Pending", "types": "", "provider_order_id": "order_Kw12aEgzDn0q2g", "payment_id": null, "signature_id": null, "created_at": "2022-12-25T04:45:25.536Z"}}, {"model": "web.order", "pk": 38, "fields": {"user": "USK07595", "amount": 1.0, "status": "Pending", "types": "", "provider_order_id": "order_Kw134dM9vfpLFW", "payment_id": null, "signature_id": null, "created_at": "2022-12-25T04:45:53.399Z"}}, {"model": "web.order", "pk": 39, "fields": {"user": "USK07595", "amount": 1.0, "status": "Pending", "types": "", "provider_order_id": "order_Kw13NO40lw1XQ2", "payment_id": null, "signature_id": null, "created_at": "2022-12-25T04:46:10.582Z"}}, {"model": "web.order", "pk": 40, "fields": {"user": "USK05494", "amount": 1.0, "status": "Pending", "types": "", "provider_order_id": "order_Kw13dq0BP7I0u2", "payment_id": null, "signature_id": null, "created_at": "2022-12-25T04:46:25.643Z"}}, {"model": "web.order", "pk": 41, "fields": {"user": "USK05494", "amount": 1.0, "status": "Success", "types": "", "provider_order_id": "order_Kw13eRWSRW4EzY", "payment_id": "pay_Kw13vtKXIWOGnX", "signature_id": "82862963b59563506f743be770d2e8096bed86b05235fd1afd79e124b5d17d3c", "created_at": "2022-12-25T04:46:26.232Z"}}, {"model": "web.order", "pk": 42, "fields": {"user": "USK07595", "amount": 1.0, "status": "Pending", "types": "", "provider_order_id": "order_Kw17zFYOUkrhkp", "payment_id": null, "signature_id": null, "created_at": "2022-12-25T04:50:32.457Z"}}, {"model": "web.order", "pk": 43, "fields": {"user": "USK07595", "amount": 1.0, "status": "Pending", "types": "", "provider_order_id": "order_Kw18XKo2WM256l", "payment_id": null, "signature_id": null, "created_at": "2022-12-25T04:51:03.678Z"}}, {"model": "web.order", "pk": 44, "fields": {"user": "USK07595", "amount": 1.0, "status": "Pending", "types": "", "provider_order_id": "order_Kw19iVICnOdgTc", "payment_id": null, "signature_id": null, "created_at": "2022-12-25T04:52:10.731Z"}}, {"model": "web.order", "pk": 45, "fields": {"user": "USK07595", "amount": 1.0, "status": "Pending", "types": "", "provider_order_id": "order_Kw1A6cnoyNRT7i", "payment_id": null, "signature_id": null, "created_at": "2022-12-25T04:52:32.840Z"}}, {"model": "web.order", "pk": 46, "fields": {"user": "USK07595", "amount": 1.0, "status": "Pending", "types": "", "provider_order_id": "order_Kw1ADdDfn78CqK", "payment_id": null, "signature_id": null, "created_at": "2022-12-25T04:52:39.233Z"}}, {"model": "web.order", "pk": 47, "fields": {"user": "USK07595", "amount": 1.0, "status": "Success", "types": "", "provider_order_id": "order_Kw1LF28FjPwpb8", "payment_id": "pay_Kw1LSwKa9FaL8t", "signature_id": "3066c6f81356c871c96721f9d91a65727f6a861e4dbb7f47345c75c30f628fbb", "created_at": "2022-12-25T05:03:05.332Z"}}, {"model": "web.order", "pk": 48, "fields": {"user": "USK07595", "amount": 1.0, "status": "Pending", "types": "", "provider_order_id": "order_Kw1eMpjpRAOoJ1", "payment_id": null, "signature_id": null, "created_at": "2022-12-25T05:21:11.794Z"}}, {"model": "web.order", "pk": 49, "fields": {"user": "USK07595", "amount": 1.0, "status": "Pending", "types": "", "provider_order_id": "order_Kw1fcHvyAGlEPm", "payment_id": null, "signature_id": null, "created_at": "2022-12-25T05:22:22.632Z"}}, {"model": "web.order", "pk": 50, "fields": {"user": "USK07595", "amount": 1.0, "status": "Pending", "types": "", "provider_order_id": "order_Kw1fkjh1xrUdVZ", "payment_id": null, "signature_id": null, "created_at": "2022-12-25T05:22:30.384Z"}}, {"model": "web.order", "pk": 51, "fields": {"user": "USK07595", "amount": 1.0, "status": "Pending", "types": "", "provider_order_id": "order_Kw8N9DOqVRHQyv", "payment_id": null, "signature_id": null, "created_at": "2022-12-25T11:55:44.941Z"}}, {"model": "web.order", "pk": 53, "fields": {"user": "USK07595", "amount": 1.0, "status": "Pending", "types": "", "provider_order_id": "order_KwQuVNfrYVL4TK", "payment_id": null, "signature_id": null, "created_at": "2022-12-26T06:03:48.744Z"}}, {"model": "web.order", "pk": 55, "fields": {"user": "USK07595", "amount": 1.0, "status": "Pending", "types": "", "provider_order_id": "order_KwSsBll3lqfsYu", "payment_id": null, "signature_id": null, "created_at": "2022-12-26T07:59:00.341Z"}}, {"model": "web.order", "pk": 56, "fields": {"user": "USK07595", "amount": 1.0, "status": "Pending", "types": "", "provider_order_id": "order_KwV8BMvQbnhWYY", "payment_id": null, "signature_id": null, "created_at": "2022-12-26T10:11:32.015Z"}}, {"model": "web.order", "pk": 57, "fields": {"user": "USK07595", "amount": 1.0, "status": "Pending", "types": "", "provider_order_id": "order_KwVrvCTRriK0tZ", "payment_id": null, "signature_id": null, "created_at": "2022-12-26T10:54:49.994Z"}}, {"model": "web.order", "pk": 58, "fields": {"user": "USK07595", "amount": 1.0, "status": "Success", "types": "", "provider_order_id": "order_KwWGPRFwohWKDz", "payment_id": "pay_KwWITc5qqGloIj", "signature_id": "cc2c7506cc8128df5d9291a9ea7c8169862634e2b4e69927278c7b1276c4a6ab", "created_at": "2022-12-26T11:18:00.891Z"}}, {"model": "web.order", "pk": 60, "fields": {"user": "USK07595", "amount": 1.0, "status": "Pending", "types": "", "provider_order_id": "order_KwWJ6NemUNJ9m3", "payment_id": null, "signature_id": null, "created_at": "2022-12-26T11:20:33.815Z"}}, {"model": "web.order", "pk": 62, "fields": {"user": "USK07595", "amount": 1.0, "status": "Pending", "types": "", "provider_order_id": "order_KwWJx5U0b2bJDc", "payment_id": null, "signature_id": null, "created_at": "2022-12-26T11:21:22.106Z"}}, {"model": "web.order", "pk": 63, "fields": {"user": "USK07595", "amount": 1.0, "status": "Pending", "types": "", "provider_order_id": "order_KwWKBzd0tGi9ih", "payment_id": null, "signature_id": null, "created_at": "2022-12-26T11:21:35.759Z"}}, {"model": "web.order", "pk": 65, "fields": {"user": "USK07595", "amount": 1.0, "status": "Pending", "types": "", "provider_order_id": "order_KwWNOYCsI3Hoj1", "payment_id": null, "signature_id": null, "created_at": "2022-12-26T11:24:37.665Z"}}, {"model": "web.order", "pk": 66, "fields": {"user": "USK07595", "amount": 1.0, "status": "Pending", "types": "", "provider_order_id": "order_KwWNObR9nnH0uc", "payment_id": null, "signature_id": null, "created_at": "2022-12-26T11:24:37.712Z"}}, {"model": "web.order", "pk": 67, "fields": {"user": "USK07595", "amount": 1.0, "status": "Pending", "types": "", "provider_order_id": "order_KwWNOiCXHJV9vK", "payment_id": null, "signature_id": null, "created_at": "2022-12-26T11:24:37.810Z"}}, {"model": "web.order", "pk": 68, "fields": {"user": "USK07595", "amount": 1.0, "status": "Pending", "types": "", "provider_order_id": "order_KwWNOp6iUtHyri", "payment_id": null, "signature_id": null, "created_at": "2022-12-26T11:24:37.924Z"}}, {"model": "web.order", "pk": 69, "fields": {"user": "USK07595", "amount": 1.0, "status": "Pending", "types": "", "provider_order_id": "order_KwWNOqiXZ090YW", "payment_id": null, "signature_id": null, "created_at": "2022-12-26T11:24:37.959Z"}}, {"model": "web.order", "pk": 71, "fields": {"user": "USK07595", "amount": 1.0, "status": "Pending", "types": "", "provider_order_id": "order_KwWNxepsM1U5ty", "payment_id": null, "signature_id": null, "created_at": "2022-12-26T11:25:09.842Z"}}, {"model": "web.order", "pk": 72, "fields": {"user": "USK07595", "amount": 1.0, "status": "Pending", "types": "", "provider_order_id": "order_KwWNxjNA8SMyqx", "payment_id": null, "signature_id": null, "created_at": "2022-12-26T11:25:09.897Z"}}, {"model": "web.order", "pk": 73, "fields": {"user": "USK07595", "amount": 1.0, "status": "Pending", "types": "", "provider_order_id": "order_KwWNxqDUMgP4dv", "payment_id": null, "signature_id": null, "created_at": "2022-12-26T11:25:10.023Z"}}, {"model": "web.order", "pk": 74, "fields": {"user": "USK07595", "amount": 1.0, "status": "Success", "types": "", "provider_order_id": "order_KwWNy6GHgltgIf", "payment_id": "pay_KwWOs6fMCViZxg", "signature_id": "d03b34f4f17208b2f7eb23d5e992d488fb8ca4475f2e0abfd58db005db2b2c27", "created_at": "2022-12-26T11:25:10.242Z"}}, {"model": "web.order", "pk": 77, "fields": {"user": "USK07595", "amount": 1.0, "status": "Pending", "types": "", "provider_order_id": "order_KwWP4Yr3JKcwsv", "payment_id": null, "signature_id": null, "created_at": "2022-12-26T11:26:12.949Z"}}, {"model": "web.order", "pk": 78, "fields": {"user": "USK07595", "amount": 1.0, "status": "Pending", "types": "", "provider_order_id": "order_KwWcE1WMq75zrd", "payment_id": null, "signature_id": null, "created_at": "2022-12-26T11:38:40.032Z"}}, {"model": "web.order", "pk": 79, "fields": {"user": "USK07595", "amount": 1.0, "status": "Pending", "types": "", "provider_order_id": "order_KwWcE9l5MDB3rk", "payment_id": null, "signature_id": null, "created_at": "2022-12-26T11:38:40.151Z"}}, {"model": "web.order", "pk": 80, "fields": {"user": "USK07595", "amount": 1.0, "status": "Pending", "types": "", "provider_order_id": "order_KwWcEAS18cJMJV", "payment_id": null, "signature_id": null, "created_at": "2022-12-26T11:38:40.161Z"}}, {"model": "web.order", "pk": 81, "fields": {"user": "USK07595", "amount": 1.0, "status": "Pending", "types": "", "provider_order_id": "order_KwWcEAvTrfdB4n", "payment_id": null, "signature_id": null, "created_at": "2022-12-26T11:38:40.166Z"}}, {"model": "web.order", "pk": 82, "fields": {"user": "USK07595", "amount": 1.0, "status": "Pending", "types": "", "provider_order_id": "order_KwWcEGeyScncD6", "payment_id": null, "signature_id": null, "created_at": "2022-12-26T11:38:40.248Z"}}, {"model": "web.order", "pk": 83, "fields": {"user": "USK07595", "amount": 1.0, "status": "Pending", "types": "", "provider_order_id": "order_KwWcETV0DgMOoQ", "payment_id": null, "signature_id": null, "created_at": "2022-12-26T11:38:40.438Z"}}, {"model": "web.order", "pk": 84, "fields": {"user": "USK07595", "amount": 1.0, "status": "Pending", "types": "", "provider_order_id": "order_KwWcEaasEBNofO", "payment_id": null, "signature_id": null, "created_at": "2022-12-26T11:38:40.540Z"}}, {"model": "web.order", "pk": 85, "fields": {"user": "USK07595", "amount": 1.0, "status": "Pending", "types": "", "provider_order_id": "order_KwWcEo2rgX8bVU", "payment_id": null, "signature_id": null, "created_at": "2022-12-26T11:38:40.749Z"}}, {"model": "web.order", "pk": 86, "fields": {"user": "USK07595", "amount": 1.0, "status": "Pending", "types": "", "provider_order_id": "order_KwWcFC4CTuikLC", "payment_id": null, "signature_id": null, "created_at": "2022-12-26T11:38:41.096Z"}}, {"model": "web.order", "pk": 87, "fields": {"user": "USK07595", "amount": 1.0, "status": "Pending", "types": "", "provider_order_id": "order_KwWcFQEbSOcd0K", "payment_id": null, "signature_id": null, "created_at": "2022-12-26T11:38:41.322Z"}}, {"model": "web.order", "pk": 88, "fields": {"user": "USK07595", "amount": 1.0, "status": "Pending", "types": "", "provider_order_id": "order_KwWcFejeMGvLTw", "payment_id": null, "signature_id": null, "created_at": "2022-12-26T11:38:41.525Z"}}, {"model": "web.order", "pk": 89, "fields": {"user": "USK07595", "amount": 1.0, "status": "Pending", "types": "", "provider_order_id": "order_KwWcG5SLfpKYlg", "payment_id": null, "signature_id": null, "created_at": "2022-12-26T11:38:41.918Z"}}, {"model": "web.order", "pk": 90, "fields": {"user": "USK07595", "amount": 1.0, "status": "Pending", "types": "", "provider_order_id": "order_KwWcGDpIUVMppX", "payment_id": null, "signature_id": null, "created_at": "2022-12-26T11:38:42.032Z"}}, {"model": "web.order", "pk": 91, "fields": {"user": "USK07595", "amount": 1.0, "status": "Pending", "types": "", "provider_order_id": "order_KwWcMsakOQHteC", "payment_id": null, "signature_id": null, "created_at": "2022-12-26T11:38:48.149Z"}}, {"model": "web.order", "pk": 92, "fields": {"user": "USK07595", "amount": 1.0, "status": "Pending", "types": "", "provider_order_id": "order_KwWcN6NnlIeySO", "payment_id": null, "signature_id": null, "created_at": "2022-12-26T11:38:48.338Z"}}, {"model": "web.order", "pk": 93, "fields": {"user": "USK07595", "amount": 1.0, "status": "Pending", "types": "", "provider_order_id": "order_KwWcNJp5Wv99DD", "payment_id": null, "signature_id": null, "created_at": "2022-12-26T11:38:48.546Z"}}, {"model": "web.order", "pk": 94, "fields": {"user": "USK07595", "amount": 1.0, "status": "Pending", "types": "", "provider_order_id": "order_KwWcaKHRDJjw1s", "payment_id": null, "signature_id": null, "created_at": "2022-12-26T11:39:00.475Z"}}, {"model": "web.order", "pk": 95, "fields": {"user": "USK07595", "amount": 1.0, "status": "Pending", "types": "", "provider_order_id": "order_KwWcabeOxAuckk", "payment_id": null, "signature_id": null, "created_at": "2022-12-26T11:39:00.716Z"}}, {"model": "web.order", "pk": 96, "fields": {"user": "USK07595", "amount": 1.0, "status": "Pending", "types": "", "provider_order_id": "order_KwWcakvIs04TCl", "payment_id": null, "signature_id": null, "created_at": "2022-12-26T11:39:00.852Z"}}, {"model": "web.order", "pk": 97, "fields": {"user": "USK07595", "amount": 1.0, "status": "Pending", "types": "", "provider_order_id": "order_KwWcawpYgd4Hbn", "payment_id": null, "signature_id": null, "created_at": "2022-12-26T11:39:01.032Z"}}, {"model": "web.order", "pk": 98, "fields": {"user": "USK07595", "amount": 1.0, "status": "Pending", "types": "", "provider_order_id": "order_KwWcbINf0Gkt1J", "payment_id": null, "signature_id": null, "created_at": "2022-12-26T11:39:01.357Z"}}, {"model": "web.order", "pk": 99, "fields": {"user": "USK07595", "amount": 1.0, "status": "Pending", "types": "", "provider_order_id": "order_KwWcbanEzGP7nv", "payment_id": null, "signature_id": null, "created_at": "2022-12-26T11:39:01.622Z"}}, {"model": "web.order", "pk": 100, "fields": {"user": "USK07595", "amount": 1.0, "status": "Pending", "types": "", "provider_order_id": "order_KwWcbrSnI19frf", "payment_id": null, "signature_id": null, "created_at": "2022-12-26T11:39:01.860Z"}}, {"model": "web.order", "pk": 101, "fields": {"user": "USK07595", "amount": 1.0, "status": "Pending", "types": "", "provider_order_id": "order_KwWccBrSQx1uf6", "payment_id": null, "signature_id": null, "created_at": "2022-12-26T11:39:02.163Z"}}, {"model": "web.order", "pk": 102, "fields": {"user": "USK07595", "amount": 1.0, "status": "Pending", "types": "", "provider_order_id": "order_KwWccaq5bh3U71", "payment_id": null, "signature_id": null, "created_at": "2022-12-26T11:39:02.537Z"}}, {"model": "web.order", "pk": 103, "fields": {"user": "USK07595", "amount": 1.0, "status": "Pending", "types": "", "provider_order_id": "order_KwWcdBrKHXFsDF", "payment_id": null, "signature_id": null, "created_at": "2022-12-26T11:39:03.092Z"}}, {"model": "web.order", "pk": 104, "fields": {"user": "USK07595", "amount": 1.0, "status": "Success", "types": "", "provider_order_id": "order_KwWcxW2L4H7bn2", "payment_id": "pay_KwWf0smY9Jb2LW", "signature_id": "8bb38186479ee8f0e8e66e31ff3fbc1314b2d53dcd6eaf26d2277f3867193c8f", "created_at": "2022-12-26T11:39:21.709Z"}}, {"model": "web.order", "pk": 105, "fields": {"user": "USK07595", "amount": 1.0, "status": "Pending", "types": "", "provider_order_id": "order_KwWcxbSQ5ABmIO", "payment_id": null, "signature_id": null, "created_at": "2022-12-26T11:39:21.788Z"}}, {"model": "web.order", "pk": 106, "fields": {"user": "USK07595", "amount": 1.0, "status": "Pending", "types": "", "provider_order_id": "order_KwWcxjlDZWar4d", "payment_id": null, "signature_id": null, "created_at": "2022-12-26T11:39:21.911Z"}}, {"model": "web.order", "pk": 107, "fields": {"user": "USK07595", "amount": 1.0, "status": "Success", "types": "", "provider_order_id": "order_KwWgin8fN5whqw", "payment_id": "pay_KwWhfeVKWaMM80", "signature_id": "9ac1981e08b1f28dd8f4409b4abe1deb44adb9c527867226e141eb8b1a7b0ad5", "created_at": "2022-12-26T11:42:55.427Z"}}, {"model": "web.order", "pk": 108, "fields": {"user": "USK07595", "amount": 1.0, "status": "Pending", "types": "", "provider_order_id": "order_KwWholGpOo3Qoq", "payment_id": null, "signature_id": null, "created_at": "2022-12-26T11:43:57.684Z"}}, {"model": "web.order", "pk": 109, "fields": {"user": "USK07595", "amount": 1.0, "status": "Pending", "types": "", "provider_order_id": "order_KwWkxF4NvZe8GW", "payment_id": null, "signature_id": null, "created_at": "2022-12-26T11:46:55.853Z"}}, {"model": "web.order", "pk": 110, "fields": {"user": "USK07595", "amount": 1.0, "status": "Pending", "types": "", "provider_order_id": "order_KwWkxGKhD5aiJ8", "payment_id": null, "signature_id": null, "created_at": "2022-12-26T11:46:55.880Z"}}, {"model": "web.order", "pk": 111, "fields": {"user": "USK07595", "amount": 1.0, "status": "Pending", "types": "", "provider_order_id": "order_KwWkxGleC8TMsx", "payment_id": null, "signature_id": null, "created_at": "2022-12-26T11:46:55.890Z"}}, {"model": "web.order", "pk": 112, "fields": {"user": "USK07595", "amount": 1.0, "status": "Pending", "types": "", "provider_order_id": "order_KwWkxHDZqBaDF3", "payment_id": null, "signature_id": null, "created_at": "2022-12-26T11:46:55.897Z"}}, {"model": "web.order", "pk": 113, "fields": {"user": "USK07595", "amount": 1.0, "status": "Pending", "types": "", "provider_order_id": "order_KwWkxIaSw26ZPr", "payment_id": null, "signature_id": null, "created_at": "2022-12-26T11:46:55.926Z"}}, {"model": "web.order", "pk": 114, "fields": {"user": "USK07595", "amount": 1.0, "status": "Pending", "types": "", "provider_order_id": "order_KwWkxJckB9iMe4", "payment_id": null, "signature_id": null, "created_at": "2022-12-26T11:46:55.940Z"}}, {"model": "web.order", "pk": 115, "fields": {"user": "USK07595", "amount": 1.0, "status": "Pending", "types": "", "provider_order_id": "order_KwWkxJqvnSREx5", "payment_id": null, "signature_id": null, "created_at": "2022-12-26T11:46:55.940Z"}}, {"model": "web.order", "pk": 116, "fields": {"user": "USK07595", "amount": 1.0, "status": "Pending", "types": "", "provider_order_id": "order_KwWkxIV9DpMI2w", "payment_id": null, "signature_id": null, "created_at": "2022-12-26T11:46:55.941Z"}}, {"model": "web.order", "pk": 117, "fields": {"user": "USK07595", "amount": 1.0, "status": "Pending", "types": "", "provider_order_id": "order_KwWkxYKJdaDzEO", "payment_id": null, "signature_id": null, "created_at": "2022-12-26T11:46:56.137Z"}}, {"model": "web.order", "pk": 118, "fields": {"user": "USK07595", "amount": 1.0, "status": "Pending", "types": "", "provider_order_id": "order_KwWl0mAOJx0IvN", "payment_id": null, "signature_id": null, "created_at": "2022-12-26T11:46:59.088Z"}}, {"model": "web.order", "pk": 119, "fields": {"user": "USK07595", "amount": 1.0, "status": "Pending", "types": "", "provider_order_id": "order_KwWl1KsVjbz55U", "payment_id": null, "signature_id": null, "created_at": "2022-12-26T11:46:59.605Z"}}, {"model": "web.order", "pk": 120, "fields": {"user": "USK07595", "amount": 1.0, "status": "Success", "types": "", "provider_order_id": "order_KwWl1uGvwarehd", "payment_id": "pay_KwWmE2Hw2eVfBF", "signature_id": "65b0d8a6f98800706868940c0c4cc2d05f9151b900b8d569dc467a648430e01a", "created_at": "2022-12-26T11:47:00.132Z"}}, {"model": "web.order", "pk": 121, "fields": {"user": "USK07595", "amount": 1.0, "status": "Pending", "types": "", "provider_order_id": "order_KwWmKMZqxezmBX", "payment_id": null, "signature_id": null, "created_at": "2022-12-26T11:48:13.894Z"}}, {"model": "web.order", "pk": 122, "fields": {"user": "USK07595", "amount": 1.0, "status": "Pending", "types": "", "provider_order_id": "order_KwWvgLwnw2NSW4", "payment_id": null, "signature_id": null, "created_at": "2022-12-26T11:57:05.196Z"}}, {"model": "web.order", "pk": 123, "fields": {"user": "USK07595", "amount": 1.0, "status": "Pending", "types": "", "provider_order_id": "order_KwWvgOqfh46aog", "payment_id": null, "signature_id": null, "created_at": "2022-12-26T11:57:05.232Z"}}, {"model": "web.order", "pk": 124, "fields": {"user": "USK07595", "amount": 1.0, "status": "Pending", "types": "", "provider_order_id": "order_KwWvgPYshzlini", "payment_id": null, "signature_id": null, "created_at": "2022-12-26T11:57:05.247Z"}}, {"model": "web.order", "pk": 125, "fields": {"user": "USK07595", "amount": 1.0, "status": "Pending", "types": "", "provider_order_id": "order_KwWvgPinapddOu", "payment_id": null, "signature_id": null, "created_at": "2022-12-26T11:57:05.248Z"}}, {"model": "web.order", "pk": 126, "fields": {"user": "USK07595", "amount": 1.0, "status": "Pending", "types": "", "provider_order_id": "order_KwWvgRZPf9qOQW", "payment_id": null, "signature_id": null, "created_at": "2022-12-26T11:57:05.283Z"}}, {"model": "web.order", "pk": 127, "fields": {"user": "USK07595", "amount": 1.0, "status": "Pending", "types": "", "provider_order_id": "order_KwWvgTXT50AORa", "payment_id": null, "signature_id": null, "created_at": "2022-12-26T11:57:05.295Z"}}, {"model": "web.order", "pk": 128, "fields": {"user": "USK07595", "amount": 1.0, "status": "Pending", "types": "", "provider_order_id": "order_KwWvgbmgOxEB74", "payment_id": null, "signature_id": null, "created_at": "2022-12-26T11:57:05.456Z"}}, {"model": "web.order", "pk": 129, "fields": {"user": "USK07595", "amount": 1.0, "status": "Pending", "types": "", "provider_order_id": "order_KwWvgjXUZxiDQZ", "payment_id": null, "signature_id": null, "created_at": "2022-12-26T11:57:05.544Z"}}, {"model": "web.order", "pk": 130, "fields": {"user": "USK07595", "amount": 1.0, "status": "Pending", "types": "", "provider_order_id": "order_KwWvndJDWTQkQq", "payment_id": null, "signature_id": null, "created_at": "2022-12-26T11:57:11.853Z"}}, {"model": "web.order", "pk": 131, "fields": {"user": "USK07595", "amount": 1.0, "status": "Success", "types": "", "provider_order_id": "order_KwWvnpF4mn9T8l", "payment_id": "pay_KwWwlSPFPfhNTT", "signature_id": "65f62f37d630e613a958ca58cab199c616c695ae7f2642e3b5cebe898df40d74", "created_at": "2022-12-26T11:57:12.026Z"}}, {"model": "web.order", "pk": 132, "fields": {"user": "USK07595", "amount": 1.0, "status": "Pending", "types": "", "provider_order_id": "order_KwWvrJwfyoheuA", "payment_id": null, "signature_id": null, "created_at": "2022-12-26T11:57:15.238Z"}}, {"model": "web.order", "pk": 133, "fields": {"user": "USK07595", "amount": 1.0, "status": "Pending", "types": "", "provider_order_id": "order_KwWwwyxDLkchDm", "payment_id": null, "signature_id": null, "created_at": "2022-12-26T11:58:17.214Z"}}, {"model": "web.order", "pk": 134, "fields": {"user": "USK07595", "amount": 1.0, "status": "Pending", "types": "", "provider_order_id": "order_KwaAWKKlGb8CXS", "payment_id": null, "signature_id": null, "created_at": "2022-12-26T15:07:12.852Z"}}, {"model": "web.order", "pk": 135, "fields": {"user": "USK05656", "amount": 1.0, "status": "Pending", "types": "", "provider_order_id": "order_KwaB9lOMKfBawe", "payment_id": null, "signature_id": null, "created_at": "2022-12-26T15:07:48.977Z"}}, {"model": "web.order", "pk": 136, "fields": {"user": "USK05656", "amount": 1.0, "status": "Pending", "types": "", "provider_order_id": "order_KwaJVMt3OeNleO", "payment_id": null, "signature_id": null, "created_at": "2022-12-26T15:15:43.180Z"}}, {"model": "web.order", "pk": 137, "fields": {"user": "USK07595", "amount": 1.0, "status": "Pending", "types": "", "provider_order_id": "order_KwnNLWgjA81iTU", "payment_id": null, "signature_id": null, "created_at": "2022-12-27T04:02:22.348Z"}}, {"model": "web.order", "pk": 138, "fields": {"user": "USK07595", "amount": 1.0, "status": "Pending", "types": "", "provider_order_id": "order_KwnNPVjcUVfrxE", "payment_id": null, "signature_id": null, "created_at": "2022-12-27T04:02:25.986Z"}}, {"model": "web.order", "pk": 139, "fields": {"user": "USK07595", "amount": 1.0, "status": "Success", "types": "", "provider_order_id": "order_KwnNPht6htcSaN", "payment_id": "pay_KwnOG9oP0qE1Nb", "signature_id": "1df3adcf11fb618a5e8b4d4ba51b032d94dc9db511d56ce3eef3cf899064894b", "created_at": "2022-12-27T04:02:26.179Z"}}, {"model": "web.order", "pk": 140, "fields": {"user": "USK07595", "amount": 1.0, "status": "Pending", "types": "", "provider_order_id": "order_KwnNPoPXLMsLNi", "payment_id": null, "signature_id": null, "created_at": "2022-12-27T04:02:26.277Z"}}, {"model": "web.order", "pk": 141, "fields": {"user": "USK05656", "amount": 1.0, "status": "Pending", "types": "", "provider_order_id": "order_KwohfvFcZwAyqM", "payment_id": null, "signature_id": null, "created_at": "2022-12-27T05:20:18.653Z"}}, {"model": "web.order", "pk": 142, "fields": {"user": "USK05656", "amount": 1.0, "status": "Pending", "types": "", "provider_order_id": "order_Kwolqf0y0kFNTs", "payment_id": null, "signature_id": null, "created_at": "2022-12-27T05:24:15.688Z"}}, {"model": "web.order", "pk": 143, "fields": {"user": "USK05656", "amount": 1.0, "status": "Pending", "types": "", "provider_order_id": "order_Kwoz9kJAerT6eq", "payment_id": null, "signature_id": null, "created_at": "2022-12-27T05:36:51.572Z"}}, {"model": "web.order", "pk": 144, "fields": {"user": "USK05656", "amount": 1.0, "status": "Pending", "types": "", "provider_order_id": "order_KwozI6uXL7j7Xl", "payment_id": null, "signature_id": null, "created_at": "2022-12-27T05:36:59.239Z"}}, {"model": "web.order", "pk": 145, "fields": {"user": "USK05656", "amount": 1.0, "status": "Success", "types": "", "provider_order_id": "order_KwozaxWPTuvYji", "payment_id": "pay_Kwp0JF0yodsMX2", "signature_id": "fd07c03de141bd453ecd2c0fb07197f0e302d735018f3ae2638e9a78c47fcb2d", "created_at": "2022-12-27T05:37:16.511Z"}}, {"model": "web.order", "pk": 149, "fields": {"user": "USK05480", "amount": 1499.0, "status": "Pending", "types": "", "provider_order_id": "order_Kwse6DE2HFNHnG", "payment_id": null, "signature_id": null, "created_at": "2022-12-27T09:11:41.996Z"}}, {"model": "web.order", "pk": 155, "fields": {"user": "USK09417", "amount": 1499.0, "status": "Pending", "types": "", "provider_order_id": "order_KwxDbhP1azLNaL", "payment_id": null, "signature_id": null, "created_at": "2022-12-27T13:40:05.310Z"}}, {"model": "web.order", "pk": 156, "fields": {"user": "USK02952", "amount": 1499.0, "status": "Pending", "types": "", "provider_order_id": "order_KwxFH3Cbs8ZQg9", "payment_id": null, "signature_id": null, "created_at": "2022-12-27T13:41:39.982Z"}}, {"model": "web.order", "pk": 158, "fields": {"user": "USK02952", "amount": 1499.0, "status": "Pending", "types": "", "provider_order_id": "order_KwxRFc99HKmjJO", "payment_id": null, "signature_id": null, "created_at": "2022-12-27T13:53:00.279Z"}}, {"model": "web.order", "pk": 159, "fields": {"user": "USK05315", "amount": 1499.0, "status": "Pending", "types": "", "provider_order_id": "order_KwxVSEHMy9qfqy", "payment_id": null, "signature_id": null, "created_at": "2022-12-27T13:56:59.038Z"}}, {"model": "web.order", "pk": 160, "fields": {"user": "USK09417", "amount": 1499.0, "status": "Pending", "types": "", "provider_order_id": "order_KwxWqYuRhyOWon", "payment_id": null, "signature_id": null, "created_at": "2022-12-27T13:58:18.126Z"}}, {"model": "web.order", "pk": 168, "fields": {"user": "USK09417", "amount": 1499.0, "status": "Pending", "types": "", "provider_order_id": "order_KxEtVcVNLBgTAI", "payment_id": null, "signature_id": null, "created_at": "2022-12-28T06:57:32.801Z"}}, {"model": "web.order", "pk": 169, "fields": {"user": "USK09417", "amount": 1499.0, "status": "Pending", "types": "", "provider_order_id": "order_KxEtcVPEJTNmfz", "payment_id": null, "signature_id": null, "created_at": "2022-12-28T06:57:39.104Z"}}, {"model": "web.order", "pk": 170, "fields": {"user": "USK09417", "amount": 1499.0, "status": "Pending", "types": "", "provider_order_id": "order_KxI84AV1c3HQam", "payment_id": null, "signature_id": null, "created_at": "2022-12-28T10:07:24.485Z"}}, {"model": "web.order", "pk": 171, "fields": {"user": "USK09417", "amount": 1499.0, "status": "Pending", "types": "", "provider_order_id": "order_KxKfQEAaEQ0cMt", "payment_id": null, "signature_id": null, "created_at": "2022-12-28T12:36:22.365Z"}}, {"model": "web.order", "pk": 172, "fields": {"user": "USK09417", "amount": 1499.0, "status": "Pending", "types": "", "provider_order_id": "order_KxKfy3IjP52CKA", "payment_id": null, "signature_id": null, "created_at": "2022-12-28T12:36:53.321Z"}}, {"model": "web.order", "pk": 173, "fields": {"user": "USK09417", "amount": 1499.0, "status": "Pending", "types": "", "provider_order_id": "order_KxKgHUF6ugKl69", "payment_id": null, "signature_id": null, "created_at": "2022-12-28T12:37:11.127Z"}}, {"model": "web.order", "pk": 174, "fields": {"user": "USK09417", "amount": 1499.0, "status": "Success", "types": "", "provider_order_id": "order_KxKm77nlnWzYUs", "payment_id": "pay_KxKmumoo3v1gYW", "signature_id": "3841c86f39db21de5dfe564a2a309bae47e532c6138beb0c7a91b68981000d13", "created_at": "2022-12-28T12:42:42.434Z"}}, {"model": "web.order", "pk": 180, "fields": {"user": "USK05480", "amount": 1499.0, "status": "Pending", "types": "", "provider_order_id": "order_Kxn2WDoX7rgCio", "payment_id": null, "signature_id": null, "created_at": "2022-12-29T16:21:39.438Z"}}, {"model": "web.order", "pk": 181, "fields": {"user": "USK09417", "amount": 1499.0, "status": "Pending", "types": "", "provider_order_id": "order_Ky4KF3j21v8Tan", "payment_id": null, "signature_id": null, "created_at": "2022-12-30T09:16:13.568Z"}}]